LangChainUtility/__init__.py
LangChainUtility/logging.py
LangChainUtility/messages.py
LangChainUtility/models.py
LangChainUtility/prompts.py
LangChainUtility-0.0.1.dist-info/LICENSE
LangChainUtility-0.0.1.dist-info/METADATA
LangChainUtility-0.0.1.dist-info/WHEEL
LangChainUtility-0.0.1.dist-info/top_level.txt
LangChainUtility-0.0.1.dist-info/RECORD
